makeflatt/__init__.py
makeflatt/flatmaker.py
makeflatt-1.0.4.dist-info/LICENSE
makeflatt-1.0.4.dist-info/WHEEL
makeflatt-1.0.4.dist-info/METADATA
makeflatt-1.0.4.dist-info/RECORD
