Metadata-Version: 2.1
Name: makeflatt
Version: 1.0.4
Summary: Simple library to make your dictionary flatten
Home-page: https://github.com/jaswdr/makeflatt
License: MIT
Keywords: makeflatt,dict,dictionaries,flatten
Author: Jonathan Schweder
Author-email: jonathanschweder@gmail.com
Requires-Python: >=3.8.1,<3.12
Classifier: License :: OSI Approved :: MIT License
Classifier: Programming Language :: Python :: 3
Project-URL: Repository, https://github.com/jaswdr/makeflatt
